odoo/addons/report_label/README.rst
odoo/addons/report_label/__init__.py
odoo/addons/report_label/__manifest__.py
odoo/addons/report_label/demo/demo.xml
odoo/addons/report_label/i18n/es.po
odoo/addons/report_label/i18n/it.po
odoo/addons/report_label/i18n/report_label.pot
odoo/addons/report_label/migrations/16.0.1.0.0/pre-migration.py
odoo/addons/report_label/models/__init__.py
odoo/addons/report_label/models/ir_actions_report.py
odoo/addons/report_label/models/ir_actions_server.py
odoo/addons/report_label/models/report_paperformat_label.py
odoo/addons/report_label/readme/CONFIGURE.rst
odoo/addons/report_label/readme/CONTRIBUTORS.rst
odoo/addons/report_label/readme/DESCRIPTION.rst
odoo/addons/report_label/readme/ROADMAP.rst
odoo/addons/report_label/readme/USAGE.rst
odoo/addons/report_label/reports/report_label.xml
odoo/addons/report_label/security/ir.model.access.csv
odoo/addons/report_label/static/description/icon.png
odoo/addons/report_label/static/description/index.html
odoo/addons/report_label/static/description/ir_actions_server_form.png
odoo/addons/report_label/static/description/report_label_wizard_form.png
odoo/addons/report_label/static/description/report_paperformat_label_form.png
odoo/addons/report_label/static/description/report_result.png
odoo/addons/report_label/tests/__init__.py
odoo/addons/report_label/tests/test_report_label.py
odoo/addons/report_label/views/ir_actions_server.xml
odoo/addons/report_label/views/report_paperformat_label.xml
odoo/addons/report_label/wizards/__init__.py
odoo/addons/report_label/wizards/report_label_wizard.py
odoo/addons/report_label/wizards/report_label_wizard.xml
odoo/addons/report_label/wizards/report_label_wizard_line.py
odoo_addon_report_label-16.0.1.0.1.2.dist-info/METADATA
odoo_addon_report_label-16.0.1.0.1.2.dist-info/WHEEL
odoo_addon_report_label-16.0.1.0.1.2.dist-info/top_level.txt
odoo_addon_report_label-16.0.1.0.1.2.dist-info/RECORD
